{"imgs":[{"date":20201019,"url":"/th?id=OHR.MatiSiTemple_ZH-CN1153907273_1920x1080.jpg&rf=LaDigue_1920x1080.jpg&pid=hp","urlbase":"/th?id=OHR.MatiSiTemple_ZH-CN1153907273","cp":"马蹄寺风景区内的马蹄寺和石窟，中国甘肃省 (© Ana Flašker/Alamy)","cpl":"/search?q=%e9%a9%ac%e8%b9%84%e5%af%ba%e9%a3%8e%e6%99%af%e5%8c%ba&form=hpcapt&mkt=zh-cn","createdAt":"2020-10-26 13:55:23","updatedAt":"2020-10-26 13:55:23","next":20201020},{"date":20201020,"url":"/th?id=OHR.BLNC_ZH-CN1521633936_1920x1080.jpg&rf=LaDigue_1920x1080.jpg&pid=hp","urlbase":"/th?id=OHR.BLNC_ZH-CN1521633936","cp":"比弗湖自然中心内光秃秃的树和红盖鳞毛蕨，纽约 (© Chris Murray/Alamy)","cpl":"/search?q=%e6%af%94%e5%bc%97%e6%b9%96&form=hpcapt&mkt=zh-cn","createdAt":"2020-10-26 13:55:23","updatedAt":"2020-10-26 13:55:23","prev":20201019,"next":20201021},{"date":20201021,"url":"/th?id=OHR.ChameleonIndonesia_ZH-CN1631787171_1920x1080.jpg&rf=LaDigue_1920x1080.jpg&pid=hp","urlbase":"/th?id=OHR.ChameleonIndonesia_ZH-CN1631787171","cp":"在一株植物上行走的变色龙，印度尼西亚 (© SnapRapid/Offset by Shutterstock)","cpl":"/search?q=%e5%8f%98%e8%89%b2%e9%be%99&form=hpcapt&mkt=zh-cn","createdAt":"2020-10-26 13:55:23","updatedAt":"2020-10-26 13:55:23","prev":20201020,"next":20201022},{"date":20201022,"url":"/th?id=OHR.LauwersmeerNP_ZH-CN1771718843_1920x1080.jpg&rf=LaDigue_1920x1080.jpg&pid=hp","urlbase":"/th?id=OHR.LauwersmeerNP_ZH-CN1771718843","cp":"Lauwersmeer国家公园上空的椋鸟群，荷兰 (© Frans Lemmens/Alamy)","cpl":"/search?q=Lauwersmeer%e5%9b%bd%e5%ae%b6%e5%85%ac%e5%9b%ad&form=hpcapt&mkt=zh-cn","createdAt":"2020-10-26 13:55:23","updatedAt":"2020-10-26 13:55:23","prev":20201021,"next":20201023},{"date":20201023,"url":"/th?id=OHR.BentsGeneral_ZH-CN7629263267_1920x1080.jpg&rf=LaDigue_1920x1080.jpg&pid=hp","urlbase":"/th?id=OHR.BentsGeneral_ZH-CN7629263267","cp":"Bents的旧百货商店，加拿大萨斯喀彻温省 (© ImagineGolf/Getty Images)","cpl":"/search?q=%e8%90%a8%e6%96%af%e5%96%80%e5%bd%bb%e6%b8%a9%e7%9c%81&form=hpcapt&mkt=zh-cn","createdAt":"2020-10-26 13:55:23","updatedAt":"2020-10-26 13:55:23","prev":20201022,"next":20201024},{"date":20201024,"url":"/th?id=OHR.UNBuilding_ZH-CN7730281645_1920x1080.jpg&rf=LaDigue_1920x1080.jpg&pid=hp","urlbase":"/th?id=OHR.UNBuilding_ZH-CN7730281645","cp":"纽约市的天际线与联合国总部大楼 (© Sean Pavone/Alamy)","cpl":"/search?q=%e8%81%94%e5%90%88%e5%9b%bd%e6%80%bb%e9%83%a8%e5%a4%a7%e6%a5%bc&form=hpcapt&mkt=zh-cn","createdAt":"2020-10-26 13:55:23","updatedAt":"2020-10-26 13:55:23","prev":20201023,"next":20201025},{"date":20201025,"url":"/th?id=OHR.BCPumpkins_ZH-CN7878617476_1920x1080.jpg&rf=LaDigue_1920x1080.jpg&pid=hp","urlbase":"/th?id=OHR.BCPumpkins_ZH-CN7878617476","cp":"不列颠哥伦比亚省的一块南瓜田，加拿大 (© James Chen/Shutterstock)","cpl":"/search?q=%e5%8d%97%e7%93%9c%e7%94%b0&form=hpcapt&mkt=zh-cn","createdAt":"2020-10-26 13:55:23","updatedAt":"2020-10-26 13:55:23","prev":20201024,"next":20201026},{"date":20201026,"url":"/th?id=OHR.CorfeDorset_ZH-CN8002715956_1920x1080.jpg&rf=LaDigue_1920x1080.jpg&pid=hp","urlbase":"/th?id=OHR.CorfeDorset_ZH-CN8002715956","cp":"科夫堡，英国多塞特 (© Ross Hoddinott/Minden Pictures)","cpl":"/search?q=%e7%a7%91%e5%a4%ab%e5%a0%a1&form=hpcapt&mkt=zh-cn","createdAt":"2020-10-26 13:55:23","updatedAt":"2020-10-26 13:55:23","prev":20201025,"next":20201027},{"date":20201027,"url":"/th?id=OHR.CambronBridge_ZH-CN8106321592_1920x1080.jpg&rf=LaDigue_1920x1080.jpg&pid=hp","urlbase":"/th?id=OHR.CambronBridge_ZH-CN8106321592","cp":"亨茨维尔附近绿色山公园中的Cambron Covered Bridge，阿拉巴马州  (© Jens Lambert/Shutterstock)","cpl":"/search?q=%e4%ba%a8%e8%8c%a8%e7%bb%b4%e5%b0%94&form=hpcapt&mkt=zh-cn","createdAt":"2020-10-27 00:00:01","updatedAt":"2020-10-27 00:00:01","prev":20201026,"next":20201028},{"date":20201028,"url":"/th?id=OHR.BasilicaVoto_ZH-CN8324675706_1920x1080.jpg&rf=LaDigue_1920x1080.jpg&pid=hp","urlbase":"/th?id=OHR.BasilicaVoto_ZH-CN8324675706","cp":"国家誓言圣殿上怪诞的厄瓜多尔本土海鸟，厄瓜多尔基多 (© Henri Leduc/Getty Images)","cpl":"/search?q=%e5%9b%bd%e5%ae%b6%e8%aa%93%e8%a8%80%e5%9c%a3%e6%ae%bf&form=hpcapt&mkt=zh-cn","createdAt":"2020-10-27 23:59:44","updatedAt":"2020-10-27 23:59:44","prev":20201027}],"date":"2020-10-27 23:59:44"}
